mobync/__init__.py
mobync/diff.py
mobync/mobync.py
mobync/read_filter.py
mobync/synchronizer.py
mobync-0.2.0.dist-info/LICENSE.md
mobync-0.2.0.dist-info/METADATA
mobync-0.2.0.dist-info/WHEEL
mobync-0.2.0.dist-info/top_level.txt
mobync-0.2.0.dist-info/RECORD
