Metadata-Version: 2.1
Name: mobync
Version: 0.2.0
Summary: The Library for online-offline synchronization
Home-page: https://github.com/mobync
Author: Carlos Matheus
Author-email: mobync.lib@gmail.com
License: MIT
Platform: UNKNOWN
Classifier: License :: OSI Approved :: MIT License
Classifier: Programming Language :: Python :: 3
Classifier: Programming Language :: Python :: 3.7
